governance/__init__.py
governance/governance.py
governance-1.2.0.dist-info/LICENSE
governance-1.2.0.dist-info/METADATA
governance-1.2.0.dist-info/WHEEL
governance-1.2.0.dist-info/top_level.txt
governance-1.2.0.dist-info/RECORD
