Metadata-Version: 2.1
Name: governance
Version: 1.2.0
Summary: Automate AI Governance requirements by connecting your python notebooks directly to the Mission Control MLOps platform.
Home-page: https://github.com/airesponsibilitylab/governance_pip
Author: Ramsay Brown
Author-email: ramsay@airesponsibilitylab.com
License: UNKNOWN
Platform: UNKNOWN
Classifier: Programming Language :: Python :: 3
Classifier: License :: OSI Approved :: MIT License
Classifier: Operating System :: OS Independent
Requires-Python: >=3.6
